[
    {
        "opinion_id": "8654354",
        "author": "Goskovia",
        "recommendation": "Polecam",
        "stars": "5/5",
        "purchased": "Opinia potwierdzona zakupem",
        "opinion_date": "2018-12-01 13:31:08",
        "purchase_date": "2018-11-25 19:35:42",
        "usefull_count": "1",
        "unusefull_count": "2",
        "content": "Zestaw przyszed\u0142 solidnie zapakowany i zabezpieczony - karton bez uszkodze\u0144 i zagniece\u0144. Je\u015bli chodzi o zawarto\u015b\u0107 to ocenimy 24 grudnia , gdy\u017c jest to prezent gwiazdkowy. Mam jednak nadziej\u0119, \u017ce i zawarto\u015b\u0107 b\u0119dzie taka, jak powinna.",
        "pros": [
            "kreatywno\u015b\u0107",
            "trwa\u0142o\u015b\u0107",
            "wygl\u0105d",
            "zabawa"
        ],
        "cons": []
    },
    {
        "opinion_id": "10051112",
        "author": "Witka",
        "recommendation": "Polecam",
        "stars": "5/5",
        "purchased": "Opinia potwierdzona zakupem",
        "opinion_date": "2019-02-06 12:34:28",
        "purchase_date": "2019-01-10 20:40:16",
        "usefull_count": "0",
        "unusefull_count": "2",
        "content": "Lego jak to Lego, nie ma si\u0119 do czego przyczepi\u0107, mo\u017ce poza cen\u0105 ;) Zestaw ciekawy, ma wiele r\u00f3\u017cnych funkcji i nowych klock\u00f3w oraz rzadkie postaci. Polecam dla fan\u00f3w Minecrafta i nie tylko!",
        "pros": [
            "dobra jako\u015b\u0107",
            "trwa\u0142o\u015b\u0107",
            "wygl\u0105d",
            "zabawa"
        ],
        "cons": []
    },
    {
        "opinion_id": "8870268",
        "author": "mazi",
        "recommendation": "Polecam",
        "stars": "5/5",
        "purchased": "Opinia potwierdzona zakupem",
        "opinion_date": "2019-01-05 18:29:32",
        "purchase_date": "2018-12-16 17:44:42",
        "usefull_count": "1",
        "unusefull_count": "1",
        "content": "Lego jak to lego idealny prezent dla ka\u017cdego. Zestaw posiada\u0142 wszystkie elementy. Sk\u0142ada\u0142o si\u0119 fajnie. Dzieci zadowolone z ko\u0144cowego efektu",
        "pros": [
            "dobra jako\u015b\u0107",
            "trwa\u0142o\u015b\u0107",
            "wygl\u0105d",
            "zabawa"
        ],
        "cons": []
    },
    {
        "opinion_id": "11082757",
        "author": "alaty",
        "recommendation": "Polecam",
        "stars": "5/5",
        "purchased": "Opinia potwierdzona zakupem",
        "opinion_date": "2019-09-26 09:20:36",
        "purchase_date": "2019-09-09 16:43:27",
        "usefull_count": "0",
        "unusefull_count": "0",
        "content": "Zestaw Lego Minecraft jak ka\u017cde klocki z du\u0144skiej firmy zachwyci\u0142y mojego syna polecam. Ka\u017cdy ma\u0142y fan Minecraft powinien by\u0107 zadowolony.",
        "pros": [
            "dobra jako\u015b\u0107",
            "kreatywno\u015b\u0107",
            "wygl\u0105d",
            "zabawa"
        ],
        "cons": []
    },
    {
        "opinion_id": "7764348",
        "author": "Krzysztof",
        "recommendation": "Polecam",
        "stars": "5/5",
        "purchased": "Opinia potwierdzona zakupem",
        "opinion_date": "2018-03-26 13:43:14",
        "purchase_date": "2018-03-21 12:36:12",
        "usefull_count": "1",
        "unusefull_count": "0",
        "content": "Gratka dla fan\u00f3w Minecrafta - syn zachwycony! Wiele ciekawych szczeg\u00f3\u0142\u00f3w i nowych element\u00f3w do \u015bwiata Minecraft",
        "pros": [
            "trwa\u0142o\u015b\u0107",
            "wygl\u0105d",
            "zabawa"
        ],
        "cons": []
    },
    {
        "opinion_id": "10630603",
        "author": "U\u017cytkownik Ceneo",
        "recommendation": "Polecam",
        "stars": "5/5",
        "purchased": "Opinia potwierdzona zakupem",
        "opinion_date": "2019-06-07 14:01:52",
        "purchase_date": "2019-05-29 21:30:48",
        "usefull_count": "0",
        "unusefull_count": "0",
        "content": "jestem bardzo zadowolony - szczeg\u00f3lnie m\u00f3j syn bo to dla niego. w przysz\u0142o\u015bci kupi\u0142bym w podobny spos\u00f3b cho\u0107 jeszcze nie kupowa\u0142em przez oiternet",
        "pros": [],
        "cons": []
    },
    {
        "opinion_id": "8833539",
        "author": "Ewelina",
        "recommendation": "Polecam",
        "stars": "5/5",
        "purchased": "Opinia potwierdzona zakupem",
        "opinion_date": "2018-12-30 19:59:17",
        "purchase_date": "2018-11-29 13:59:32",
        "usefull_count": "0",
        "unusefull_count": "0",
        "content": "LEGO zosta\u0142o zakupione na prezent urodzinowy i jak najbardziej spe\u0142ni\u0142o oczekiwania. LEGO nadal trzyma wysoki poziom - klocki s\u0105 dobrze wykonane.",
        "pros": [],
        "cons": []
    },
    {
        "opinion_id": "10048471",
        "author": "pioles",
        "recommendation": "Polecam",
        "stars": "4,5/5",
        "purchased": "Opinia potwierdzona zakupem",
        "opinion_date": "2019-02-07 18:24:41",
        "purchase_date": "2019-01-15 08:51:38",
        "usefull_count": "0",
        "unusefull_count": "0",
        "content": "Porz\u0105dnie wykonane. Cena w Mall.pl bardzo dobra, pomimo tego, \u017ce LEGO jest og\u00f3lnie drogie. Portal Netheru jest cz\u0119\u015bci\u0105 wi\u0119kszej ca\u0142o\u015bci.",
        "pros": [],
        "cons": []
    },
    {
        "opinion_id": "8868812",
        "author": "U\u017cytkownik Ceneo",
        "recommendation": "Nie polecam",
        "stars": "0,5/5",
        "purchased": "Opinia potwierdzona zakupem",
        "opinion_date": "2019-01-05 13:51:16",
        "purchase_date": "2018-12-12 23:21:27",
        "usefull_count": "0",
        "unusefull_count": "0",
        "content": "Zam\u00f3wiona zabawka dla dziecka na \u015awi\u0119ta Bo\u017cego Narodzenia, podana do realizacji przez sklep. Przez 2 tygodnie brak informacji o wysy\u0142ce, braku mo\u017cliwo\u015bci wysy\u0142ki, a dziecko czeka na prezent :( i tak choinka by min\u0119\u0142a bez prezentu. Ca\u0142e szcz\u0119\u015bcie klocki lego kupione w innym sklepie, nie w Mall.pl :(",
        "pros": [],
        "cons": []
    },
    {
        "opinion_id": "13886745",
        "author": "a...a",
        "recommendation": "Nie polecam",
        "stars": "1,5/5",
        "purchased": "Opinia potwierdzona zakupem",
        "opinion_date": "2021-02-03 08:25:51",
        "purchase_date": "2021-01-16 13:17:50",
        "usefull_count": "0",
        "unusefull_count": "0",
        "content": "Niestety nie mog\u0119 wystawi\u0107 pozytywnej opinii. Towar nie dotar\u0142, poniewa\u017c okaza\u0142o si\u0119, \u017ce nie jest dost\u0119pny w sklepie i w magazynie, mimo i\u017c by\u0142 na stronie. Czeka\u0142am tydzie\u0144. Sama skontaktowa\u0142am si\u0119 mailowo z firm\u0105 i plusem jest to, \u017ce szybko otrzyma\u0142am zwrot pieni\u0119dzy na konto.",
        "pros": [],
        "cons": []
    }
]